{
  "Workspace_Density": 0,
  "Workspace_Height": 1000,
  "Workspace_Width": 1000,
  "number_of_objects": 8,
  "object_list": [
    {
      "Object_Shape": "tetris_T",
      "Object_Length": 100.0,
      "Object_Width": 100.0,
      "initial_pose": [
        778.5644472058345,
        824.3589896919642,
        3.4497771793841037
      ],
      "goal_pose": [
        639.6726915480066,
        407.2268217194061,
        2.07973386337651
      ]
    },
    {
      "Object_Shape": "tetris_S",
      "Object_Length": 100.0,
      "Object_Width": 100.0,
      "initial_pose": [
        353.30277123928533,
        322.2852103875915,
        0.9786458837569949
      ],
      "goal_pose": [
        234.36343546441728,
        398.84134599544797,
        1.3831329772327376
      ]
    },
    {
      "Object_Shape": "tetris_S",
      "Object_Length": 100.0,
      "Object_Width": 100.0,
      "initial_pose": [
        272.90131285708605,
        883.5752980572031,
        2.8452024657327435
      ],
      "goal_pose": [
        403.19401998830006,
        703.9212653667516,
        0.39907105114915664
      ]
    },
    {
      "Object_Shape": "tetris_T",
      "Object_Length": 100.0,
      "Object_Width": 100.0,
      "initial_pose": [
        688.1862429957557,
        425.52535812406234,
        4.855061685356036
      ],
      "goal_pose": [
        679.8949092909962,
        153.9657360767499,
        0.7165502772717773
      ]
    },
    {
      "Object_Shape": "tetris_Z",
      "Object_Length": 100.0,
      "Object_Width": 100.0,
      "initial_pose": [
        119.27848656308448,
        392.05690330408993,
        1.6132809783387854
      ],
      "goal_pose": [
        780.4490678879846,
        809.0292737257746,
        3.7474397903975962
      ]
    },
    {
      "Object_Shape": "tetris_T",
      "Object_Length": 100.0,
      "Object_Width": 100.0,
      "initial_pose": [
        436.5595739228283,
        660.1028279934494,
        0.4540016832379555
      ],
      "goal_pose": [
        159.7952417690447,
        802.7266904300519,
        4.82580246893201
      ]
    },
    {
      "Object_Shape": "tetris_Z",
      "Object_Length": 100.0,
      "Object_Width": 100.0,
      "initial_pose": [
        814.0339566034469,
        214.97966884456065,
        1.511206913691735
      ],
      "goal_pose": [
        864.086459558111,
        514.3565668499725,
        4.655684822920826
      ]
    },
    {
      "Object_Shape": "tetris_I",
      "Object_Length": 100.0,
      "Object_Width": 100.0,
      "initial_pose": [
        455.3527746056321,
        90.6616579168068,
        3.147022669213744
      ],
      "goal_pose": [
        261.3118707767891,
        167.78990267767358,
        2.782205362370929
      ]
    }
  ]
}