{
  "Workspace_Density": 0.35,
  "Workspace_Height": 1000,
  "Workspace_Width": 1000,
  "number_of_objects": 20,
  "object_list": [
    {
      "Object_Shape": "cuboid",
      "Object_Length": 336.5540200536007,
      "Object_Width": 336.5540200536007,
      "initial_pose": [
        761.9711061885312,
        371.7753934598744,
        5.596137081406736
      ],
      "goal_pose": [
        178.27701002680035,
        178.27701002680035,
        0
      ]
    },
    {
      "Object_Shape": "cuboid",
      "Object_Length": 111.62234062035405,
      "Object_Width": 111.62234062035405,
      "initial_pose": [
        132.42634204685422,
        473.90794207321164,
        1.337662694176149
      ],
      "goal_pose": [
        412.36519036377774,
        65.81117031017703,
        0
      ]
    },
    {
      "Object_Shape": "cuboid",
      "Object_Length": 111.62234062035405,
      "Object_Width": 111.62234062035405,
      "initial_pose": [
        309.8016355707045,
        655.3660229220692,
        0.23617640199971618
      ],
      "goal_pose": [
        533.9875309841318,
        65.81117031017703,
        0
      ]
    },
    {
      "Object_Shape": "cuboid",
      "Object_Length": 111.62234062035405,
      "Object_Width": 111.62234062035405,
      "initial_pose": [
        367.6508513811956,
        391.58174511336364,
        3.4679858271887865
      ],
      "goal_pose": [
        655.6098716044859,
        65.81117031017703,
        0
      ]
    },
    {
      "Object_Shape": "cuboid",
      "Object_Length": 111.62234062035405,
      "Object_Width": 111.62234062035405,
      "initial_pose": [
        884.7804872654168,
        565.9212193654527,
        0.9400857112093256
      ],
      "goal_pose": [
        777.2322122248399,
        65.81117031017703,
        0
      ]
    },
    {
      "Object_Shape": "cuboid",
      "Object_Length": 111.62234062035405,
      "Object_Width": 111.62234062035405,
      "initial_pose": [
        317.07555873408853,
        248.71579660411146,
        2.420815873820004
      ],
      "goal_pose": [
        898.8545528451939,
        65.81117031017703,
        0
      ]
    },
    {
      "Object_Shape": "cuboid",
      "Object_Length": 111.62234062035405,
      "Object_Width": 111.62234062035405,
      "initial_pose": [
        595.2330851954914,
        872.548429794239,
        3.587310222603435
      ],
      "goal_pose": [
        412.36519036377774,
        290.7428497434237,
        0
      ]
    },
    {
      "Object_Shape": "cuboid",
      "Object_Length": 111.62234062035405,
      "Object_Width": 111.62234062035405,
      "initial_pose": [
        309.88047835311494,
        794.2003720217162,
        3.065393745508068
      ],
      "goal_pose": [
        533.9875309841318,
        290.7428497434237,
        0
      ]
    },
    {
      "Object_Shape": "cuboid",
      "Object_Length": 111.62234062035405,
      "Object_Width": 111.62234062035405,
      "initial_pose": [
        167.9777805822742,
        86.08989481389861,
        5.8468188892496045
      ],
      "goal_pose": [
        655.6098716044859,
        290.7428497434237,
        0
      ]
    },
    {
      "Object_Shape": "cuboid",
      "Object_Length": 111.62234062035405,
      "Object_Width": 111.62234062035405,
      "initial_pose": [
        842.7964596040928,
        886.8295330752061,
        4.40582741340881
      ],
      "goal_pose": [
        777.2322122248399,
        290.7428497434237,
        0
      ]
    },
    {
      "Object_Shape": "cuboid",
      "Object_Length": 111.62234062035405,
      "Object_Width": 111.62234062035405,
      "initial_pose": [
        608.4040927724263,
        687.5610199687425,
        3.123717670936352
      ],
      "goal_pose": [
        898.8545528451939,
        290.7428497434237,
        0
      ]
    },
    {
      "Object_Shape": "cuboid",
      "Object_Length": 111.62234062035405,
      "Object_Width": 111.62234062035405,
      "initial_pose": [
        637.6174637568241,
        103.07292191548045,
        1.4757048808800644
      ],
      "goal_pose": [
        65.81117031017703,
        412.36519036377774,
        0
      ]
    },
    {
      "Object_Shape": "cuboid",
      "Object_Length": 111.62234062035405,
      "Object_Width": 111.62234062035405,
      "initial_pose": [
        446.52742373940936,
        717.4234272888586,
        4.831604324888622
      ],
      "goal_pose": [
        187.43351093053107,
        412.36519036377774,
        0
      ]
    },
    {
      "Object_Shape": "cuboid",
      "Object_Length": 111.62234062035405,
      "Object_Width": 111.62234062035405,
      "initial_pose": [
        62.92011302330902,
        838.9420877870235,
        1.6439608597754616
      ],
      "goal_pose": [
        309.0558515508851,
        412.36519036377774,
        0
      ]
    },
    {
      "Object_Shape": "cuboid",
      "Object_Length": 111.62234062035405,
      "Object_Width": 111.62234062035405,
      "initial_pose": [
        786.3632740673468,
        725.1573542378524,
        3.1102208204765134
      ],
      "goal_pose": [
        430.6781921712392,
        412.36519036377774,
        0
      ]
    },
    {
      "Object_Shape": "cuboid",
      "Object_Length": 111.62234062035405,
      "Object_Width": 111.62234062035405,
      "initial_pose": [
        113.85722838608902,
        636.8039214077161,
        3.5267910239941056
      ],
      "goal_pose": [
        552.3005327915932,
        412.36519036377774,
        0
      ]
    },
    {
      "Object_Shape": "cuboid",
      "Object_Length": 111.62234062035405,
      "Object_Width": 111.62234062035405,
      "initial_pose": [
        435.66360414814733,
        514.5444469277867,
        2.6565487272077566
      ],
      "goal_pose": [
        673.9228734119473,
        412.36519036377774,
        0
      ]
    },
    {
      "Object_Shape": "cuboid",
      "Object_Length": 111.62234062035405,
      "Object_Width": 111.62234062035405,
      "initial_pose": [
        155.82431345666558,
        294.1602948248294,
        5.634939120109458
      ],
      "goal_pose": [
        795.5452140323014,
        412.36519036377774,
        0
      ]
    },
    {
      "Object_Shape": "cuboid",
      "Object_Length": 111.62234062035405,
      "Object_Width": 111.62234062035405,
      "initial_pose": [
        453.91085297863145,
        179.91301614654597,
        2.0539757747603447
      ],
      "goal_pose": [
        917.1675546526554,
        412.36519036377774,
        0
      ]
    },
    {
      "Object_Shape": "cuboid",
      "Object_Length": 111.62234062035405,
      "Object_Width": 111.62234062035405,
      "initial_pose": [
        340.4342545416728,
        930.5513170410435,
        0.24933375982683803
      ],
      "goal_pose": [
        65.81117031017703,
        533.9875309841318,
        0
      ]
    }
  ]
}