{
  "Workspace_Density": 0.35,
  "Workspace_Height": 1000,
  "Workspace_Width": 1000,
  "number_of_objects": 40,
  "object_list": [
    {
      "Object_Shape": "cuboid",
      "Object_Length": 237.97962981549438,
      "Object_Width": 237.97962981549438,
      "initial_pose": [
        607.9710694481456,
        202.44571812440194,
        3.9641819112035663
      ],
      "goal_pose": [
        128.9898149077472,
        128.9898149077472,
        0
      ]
    },
    {
      "Object_Shape": "cuboid",
      "Object_Length": 237.97962981549438,
      "Object_Width": 237.97962981549438,
      "initial_pose": [
        323.4434902571889,
        769.4235687614663,
        0.750836356046585
      ],
      "goal_pose": [
        376.96944472324157,
        128.9898149077472,
        0
      ]
    },
    {
      "Object_Shape": "cuboid",
      "Object_Length": 78.92891398456696,
      "Object_Width": 78.92891398456696,
      "initial_pose": [
        478.1809708536594,
        361.39344783626314,
        0.34087623918061377
      ],
      "goal_pose": [
        545.4237166232723,
        49.46445699228348,
        0
      ]
    },
    {
      "Object_Shape": "cuboid",
      "Object_Length": 78.92891398456696,
      "Object_Width": 78.92891398456696,
      "initial_pose": [
        290.41929881326723,
        227.30675477558583,
        4.423716883840343
      ],
      "goal_pose": [
        634.3526306078393,
        49.46445699228348,
        0
      ]
    },
    {
      "Object_Shape": "cuboid",
      "Object_Length": 78.92891398456696,
      "Object_Width": 78.92891398456696,
      "initial_pose": [
        448.18328687913566,
        478.00081077592694,
        3.5238886991179066
      ],
      "goal_pose": [
        723.2815445924061,
        49.46445699228348,
        0
      ]
    },
    {
      "Object_Shape": "cuboid",
      "Object_Length": 78.92891398456696,
      "Object_Width": 78.92891398456696,
      "initial_pose": [
        98.37470189663888,
        850.7149243687925,
        3.145972005130891
      ],
      "goal_pose": [
        812.2104585769732,
        49.46445699228348,
        0
      ]
    },
    {
      "Object_Shape": "cuboid",
      "Object_Length": 78.92891398456696,
      "Object_Width": 78.92891398456696,
      "initial_pose": [
        651.8383640144544,
        740.7078259616417,
        4.532151480638289
      ],
      "goal_pose": [
        901.1393725615401,
        49.46445699228348,
        0
      ]
    },
    {
      "Object_Shape": "cuboid",
      "Object_Length": 78.92891398456696,
      "Object_Width": 78.92891398456696,
      "initial_pose": [
        841.1532995610488,
        436.3443963004505,
        2.1540776935058012
      ],
      "goal_pose": [
        990.0682865461072,
        49.46445699228348,
        0
      ]
    },
    {
      "Object_Shape": "cuboid",
      "Object_Length": 78.92891398456696,
      "Object_Width": 78.92891398456696,
      "initial_pose": [
        393.7134126635583,
        266.2186274665429,
        2.1039973378952657
      ],
      "goal_pose": [
        545.4237166232723,
        208.5151728232109,
        0
      ]
    },
    {
      "Object_Shape": "cuboid",
      "Object_Length": 78.92891398456696,
      "Object_Width": 78.92891398456696,
      "initial_pose": [
        564.9704376662943,
        585.0044409651439,
        0.7390137097686479
      ],
      "goal_pose": [
        634.3526306078393,
        208.5151728232109,
        0
      ]
    },
    {
      "Object_Shape": "cuboid",
      "Object_Length": 78.92891398456696,
      "Object_Width": 78.92891398456696,
      "initial_pose": [
        82.96517897668976,
        643.0800705543273,
        3.7646765553567456
      ],
      "goal_pose": [
        723.2815445924061,
        208.5151728232109,
        0
      ]
    },
    {
      "Object_Shape": "cuboid",
      "Object_Length": 78.92891398456696,
      "Object_Width": 78.92891398456696,
      "initial_pose": [
        237.34221798567722,
        589.3851188848289,
        1.3388615039884773
      ],
      "goal_pose": [
        812.2104585769732,
        208.5151728232109,
        0
      ]
    },
    {
      "Object_Shape": "cuboid",
      "Object_Length": 78.92891398456696,
      "Object_Width": 78.92891398456696,
      "initial_pose": [
        923.761124127506,
        656.6577610471644,
        2.4637792845698137
      ],
      "goal_pose": [
        901.1393725615401,
        208.5151728232109,
        0
      ]
    },
    {
      "Object_Shape": "cuboid",
      "Object_Length": 78.92891398456696,
      "Object_Width": 78.92891398456696,
      "initial_pose": [
        502.27108830728696,
        875.2763106048602,
        2.636252053602892
      ],
      "goal_pose": [
        990.0682865461072,
        208.5151728232109,
        0
      ]
    },
    {
      "Object_Shape": "cuboid",
      "Object_Length": 78.92891398456696,
      "Object_Width": 78.92891398456696,
      "initial_pose": [
        742.1812079123482,
        829.01909467611,
        4.7701552351403445
      ],
      "goal_pose": [
        49.46445699228348,
        297.44408680777786,
        0
      ]
    },
    {
      "Object_Shape": "cuboid",
      "Object_Length": 78.92891398456696,
      "Object_Width": 78.92891398456696,
      "initial_pose": [
        194.30713170851433,
        476.9470121727617,
        5.625198613694579
      ],
      "goal_pose": [
        138.39337097685043,
        297.44408680777786,
        0
      ]
    },
    {
      "Object_Shape": "cuboid",
      "Object_Length": 78.92891398456696,
      "Object_Width": 78.92891398456696,
      "initial_pose": [
        756.5633703808154,
        352.91463733250106,
        1.251848427047494
      ],
      "goal_pose": [
        227.32228496141738,
        297.44408680777786,
        0
      ]
    },
    {
      "Object_Shape": "cuboid",
      "Object_Length": 78.92891398456696,
      "Object_Width": 78.92891398456696,
      "initial_pose": [
        854.8459720653676,
        791.9656728857735,
        3.038966320145883
      ],
      "goal_pose": [
        316.25119894598436,
        297.44408680777786,
        0
      ]
    },
    {
      "Object_Shape": "cuboid",
      "Object_Length": 78.92891398456696,
      "Object_Width": 78.92891398456696,
      "initial_pose": [
        653.0687840508003,
        437.2495249363111,
        0.18121038688757718
      ],
      "goal_pose": [
        405.18011293055133,
        297.44408680777786,
        0
      ]
    },
    {
      "Object_Shape": "cuboid",
      "Object_Length": 78.92891398456696,
      "Object_Width": 78.92891398456696,
      "initial_pose": [
        446.0827803351544,
        660.7372314162698,
        3.943349045417205
      ],
      "goal_pose": [
        494.10902691511825,
        297.44408680777786,
        0
      ]
    },
    {
      "Object_Shape": "cuboid",
      "Object_Length": 78.92891398456696,
      "Object_Width": 78.92891398456696,
      "initial_pose": [
        420.4508756369164,
        942.2395736815563,
        5.067594836324801
      ],
      "goal_pose": [
        583.0379408996853,
        297.44408680777786,
        0
      ]
    },
    {
      "Object_Shape": "cuboid",
      "Object_Length": 78.92891398456696,
      "Object_Width": 78.92891398456696,
      "initial_pose": [
        791.9929688758018,
        542.1152710971969,
        0.5392379365596105
      ],
      "goal_pose": [
        671.9668548842523,
        297.44408680777786,
        0
      ]
    },
    {
      "Object_Shape": "cuboid",
      "Object_Length": 78.92891398456696,
      "Object_Width": 78.92891398456696,
      "initial_pose": [
        125.90713698973066,
        345.1337432730719,
        2.9061317487872387
      ],
      "goal_pose": [
        760.8957688688192,
        297.44408680777786,
        0
      ]
    },
    {
      "Object_Shape": "cuboid",
      "Object_Length": 78.92891398456696,
      "Object_Width": 78.92891398456696,
      "initial_pose": [
        399.1498424641029,
        144.93749859982884,
        2.9785268880221136
      ],
      "goal_pose": [
        849.8246828533862,
        297.44408680777786,
        0
      ]
    },
    {
      "Object_Shape": "cuboid",
      "Object_Length": 78.92891398456696,
      "Object_Width": 78.92891398456696,
      "initial_pose": [
        879.3224264291448,
        254.88030600421595,
        3.136137153682752
      ],
      "goal_pose": [
        938.7535968379532,
        297.44408680777786,
        0
      ]
    },
    {
      "Object_Shape": "cuboid",
      "Object_Length": 78.92891398456696,
      "Object_Width": 78.92891398456696,
      "initial_pose": [
        820.2969705115321,
        922.2237238105055,
        6.066687854823053
      ],
      "goal_pose": [
        49.46445699228348,
        386.37300079234484,
        0
      ]
    },
    {
      "Object_Shape": "cuboid",
      "Object_Length": 78.92891398456696,
      "Object_Width": 78.92891398456696,
      "initial_pose": [
        47.39675718896086,
        486.7984893774846,
        1.6194127695290919
      ],
      "goal_pose": [
        138.39337097685043,
        386.37300079234484,
        0
      ]
    },
    {
      "Object_Shape": "cuboid",
      "Object_Length": 78.92891398456696,
      "Object_Width": 78.92891398456696,
      "initial_pose": [
        352.00913406803824,
        466.518736421108,
        3.9171015688050517
      ],
      "goal_pose": [
        227.32228496141738,
        386.37300079234484,
        0
      ]
    },
    {
      "Object_Shape": "cuboid",
      "Object_Length": 78.92891398456696,
      "Object_Width": 78.92891398456696,
      "initial_pose": [
        170.7549213691395,
        225.0992714733624,
        5.522512959958292
      ],
      "goal_pose": [
        316.25119894598436,
        386.37300079234484,
        0
      ]
    },
    {
      "Object_Shape": "cuboid",
      "Object_Length": 78.92891398456696,
      "Object_Width": 78.92891398456696,
      "initial_pose": [
        854.3829713885756,
        102.5897716089339,
        3.298582523077979
      ],
      "goal_pose": [
        405.18011293055133,
        386.37300079234484,
        0
      ]
    },
    {
      "Object_Shape": "cuboid",
      "Object_Length": 78.92891398456696,
      "Object_Width": 78.92891398456696,
      "initial_pose": [
        250.64559453311375,
        319.9519497328176,
        3.39239963165626
      ],
      "goal_pose": [
        494.10902691511825,
        386.37300079234484,
        0
      ]
    },
    {
      "Object_Shape": "cuboid",
      "Object_Length": 78.92891398456696,
      "Object_Width": 78.92891398456696,
      "initial_pose": [
        929.1224706450245,
        341.88997852631906,
        4.154208690682997
      ],
      "goal_pose": [
        583.0379408996853,
        386.37300079234484,
        0
      ]
    },
    {
      "Object_Shape": "cuboid",
      "Object_Length": 78.92891398456696,
      "Object_Width": 78.92891398456696,
      "initial_pose": [
        714.8981198350596,
        624.3576727325941,
        1.4419988187374417
      ],
      "goal_pose": [
        671.9668548842523,
        386.37300079234484,
        0
      ]
    },
    {
      "Object_Shape": "cuboid",
      "Object_Length": 78.92891398456696,
      "Object_Width": 78.92891398456696,
      "initial_pose": [
        55.4662468806687,
        157.4005886749763,
        5.0597790479560505
      ],
      "goal_pose": [
        760.8957688688192,
        386.37300079234484,
        0
      ]
    },
    {
      "Object_Shape": "cuboid",
      "Object_Length": 78.92891398456696,
      "Object_Width": 78.92891398456696,
      "initial_pose": [
        153.8342932429748,
        693.183784789005,
        3.8760327913247705
      ],
      "goal_pose": [
        849.8246828533862,
        386.37300079234484,
        0
      ]
    },
    {
      "Object_Shape": "cuboid",
      "Object_Length": 78.92891398456696,
      "Object_Width": 78.92891398456696,
      "initial_pose": [
        641.3737328540541,
        901.2154054450741,
        1.2250325252965775
      ],
      "goal_pose": [
        938.7535968379532,
        386.37300079234484,
        0
      ]
    },
    {
      "Object_Shape": "cuboid",
      "Object_Length": 78.92891398456696,
      "Object_Width": 78.92891398456696,
      "initial_pose": [
        193.98803799094034,
        99.53014823855399,
        6.075247100045228
      ],
      "goal_pose": [
        49.46445699228348,
        475.3019147769118,
        0
      ]
    },
    {
      "Object_Shape": "cuboid",
      "Object_Length": 78.92891398456696,
      "Object_Width": 78.92891398456696,
      "initial_pose": [
        952.383911407958,
        500.460347164531,
        6.065616893718335
      ],
      "goal_pose": [
        138.39337097685043,
        475.3019147769118,
        0
      ]
    },
    {
      "Object_Shape": "cuboid",
      "Object_Length": 78.92891398456696,
      "Object_Width": 78.92891398456696,
      "initial_pose": [
        956.3266300403907,
        113.94868476540087,
        3.1248262820894825
      ],
      "goal_pose": [
        227.32228496141738,
        475.3019147769118,
        0
      ]
    },
    {
      "Object_Shape": "cuboid",
      "Object_Length": 78.92891398456696,
      "Object_Width": 78.92891398456696,
      "initial_pose": [
        923.4752071442208,
        906.677918139474,
        3.264895541287907
      ],
      "goal_pose": [
        316.25119894598436,
        475.3019147769118,
        0
      ]
    }
  ]
}