{
  "Workspace_Density": 0.4,
  "Workspace_Height": 1000,
  "Workspace_Width": 1000,
  "number_of_objects": 40,
  "object_list": [
    {
      "Object_Shape": "cuboid",
      "Object_Length": 254.41092565739217,
      "Object_Width": 254.41092565739217,
      "initial_pose": [
        843.6386291314027,
        442.5882780269782,
        6.04292538584151
      ],
      "goal_pose": [
        137.20546282869608,
        137.20546282869608,
        0
      ]
    },
    {
      "Object_Shape": "cuboid",
      "Object_Length": 254.41092565739217,
      "Object_Width": 254.41092565739217,
      "initial_pose": [
        392.68662632585307,
        508.50628618128536,
        4.047662895084872
      ],
      "goal_pose": [
        401.6163884860882,
        137.20546282869608,
        0
      ]
    },
    {
      "Object_Shape": "cuboid",
      "Object_Length": 84.37855829725716,
      "Object_Width": 84.37855829725716,
      "initial_pose": [
        735.4137031873017,
        749.4835170083157,
        4.225232896849295
      ],
      "goal_pose": [
        581.011130463413,
        52.18927914862858,
        0
      ]
    },
    {
      "Object_Shape": "cuboid",
      "Object_Length": 84.37855829725716,
      "Object_Width": 84.37855829725716,
      "initial_pose": [
        338.51597450142503,
        132.02930855502558,
        1.4191535448676964
      ],
      "goal_pose": [
        675.3896887606701,
        52.18927914862858,
        0
      ]
    },
    {
      "Object_Shape": "cuboid",
      "Object_Length": 84.37855829725716,
      "Object_Width": 84.37855829725716,
      "initial_pose": [
        929.2150588005547,
        615.8903494157888,
        5.074101715962966
      ],
      "goal_pose": [
        769.7682470579273,
        52.18927914862858,
        0
      ]
    },
    {
      "Object_Shape": "cuboid",
      "Object_Length": 84.37855829725716,
      "Object_Width": 84.37855829725716,
      "initial_pose": [
        249.16498506662265,
        109.52044227369262,
        1.4436115294741274
      ],
      "goal_pose": [
        864.1468053551845,
        52.18927914862858,
        0
      ]
    },
    {
      "Object_Shape": "cuboid",
      "Object_Length": 84.37855829725716,
      "Object_Width": 84.37855829725716,
      "initial_pose": [
        208.14597594830707,
        588.7380044007532,
        3.0604016157358664
      ],
      "goal_pose": [
        958.5253636524416,
        52.18927914862858,
        0
      ]
    },
    {
      "Object_Shape": "cuboid",
      "Object_Length": 84.37855829725716,
      "Object_Width": 84.37855829725716,
      "initial_pose": [
        72.87675781195124,
        188.4500963934551,
        2.795386747851079
      ],
      "goal_pose": [
        581.011130463413,
        222.2216465087636,
        0
      ]
    },
    {
      "Object_Shape": "cuboid",
      "Object_Length": 84.37855829725716,
      "Object_Width": 84.37855829725716,
      "initial_pose": [
        447.47357697170264,
        848.2989119108609,
        1.7735619131624514
      ],
      "goal_pose": [
        675.3896887606701,
        222.2216465087636,
        0
      ]
    },
    {
      "Object_Shape": "cuboid",
      "Object_Length": 84.37855829725716,
      "Object_Width": 84.37855829725716,
      "initial_pose": [
        905.2772457133534,
        50.14994395745309,
        3.2044655736795367
      ],
      "goal_pose": [
        769.7682470579273,
        222.2216465087636,
        0
      ]
    },
    {
      "Object_Shape": "cuboid",
      "Object_Length": 84.37855829725716,
      "Object_Width": 84.37855829725716,
      "initial_pose": [
        605.607143109864,
        85.30271561532842,
        1.8526790665354778
      ],
      "goal_pose": [
        864.1468053551845,
        222.2216465087636,
        0
      ]
    },
    {
      "Object_Shape": "cuboid",
      "Object_Length": 84.37855829725716,
      "Object_Width": 84.37855829725716,
      "initial_pose": [
        85.50334890107814,
        655.4647726399529,
        2.047737754046399
      ],
      "goal_pose": [
        958.5253636524416,
        222.2216465087636,
        0
      ]
    },
    {
      "Object_Shape": "cuboid",
      "Object_Length": 84.37855829725716,
      "Object_Width": 84.37855829725716,
      "initial_pose": [
        572.9241809563825,
        643.3696374626747,
        3.9047443342709105
      ],
      "goal_pose": [
        52.18927914862858,
        316.6002048060207,
        0
      ]
    },
    {
      "Object_Shape": "cuboid",
      "Object_Length": 84.37855829725716,
      "Object_Width": 84.37855829725716,
      "initial_pose": [
        600.5709175169723,
        384.252587490846,
        0.17153629714079577
      ],
      "goal_pose": [
        146.56783744588574,
        316.6002048060207,
        0
      ]
    },
    {
      "Object_Shape": "cuboid",
      "Object_Length": 84.37855829725716,
      "Object_Width": 84.37855829725716,
      "initial_pose": [
        730.9356196304033,
        151.8628842652683,
        1.5911060148554668
      ],
      "goal_pose": [
        240.94639574314292,
        316.6002048060207,
        0
      ]
    },
    {
      "Object_Shape": "cuboid",
      "Object_Length": 84.37855829725716,
      "Object_Width": 84.37855829725716,
      "initial_pose": [
        280.7936225250789,
        823.2472497747631,
        0.2771964680149797
      ],
      "goal_pose": [
        335.32495404040003,
        316.6002048060207,
        0
      ]
    },
    {
      "Object_Shape": "cuboid",
      "Object_Length": 84.37855829725716,
      "Object_Width": 84.37855829725716,
      "initial_pose": [
        244.29203448982383,
        340.3917770593861,
        1.7615656880275334
      ],
      "goal_pose": [
        429.7035123376572,
        316.6002048060207,
        0
      ]
    },
    {
      "Object_Shape": "cuboid",
      "Object_Length": 84.37855829725716,
      "Object_Width": 84.37855829725716,
      "initial_pose": [
        795.0423208378154,
        904.866374040929,
        3.25187114534149
      ],
      "goal_pose": [
        524.0820706349144,
        316.6002048060207,
        0
      ]
    },
    {
      "Object_Shape": "cuboid",
      "Object_Length": 84.37855829725716,
      "Object_Width": 84.37855829725716,
      "initial_pose": [
        211.06388454333802,
        937.1325534492083,
        4.632139587851985
      ],
      "goal_pose": [
        618.4606289321715,
        316.6002048060207,
        0
      ]
    },
    {
      "Object_Shape": "cuboid",
      "Object_Length": 84.37855829725716,
      "Object_Width": 84.37855829725716,
      "initial_pose": [
        746.612995410128,
        46.48412370089139,
        4.765586223331964
      ],
      "goal_pose": [
        712.8391872294287,
        316.6002048060207,
        0
      ]
    },
    {
      "Object_Shape": "cuboid",
      "Object_Length": 84.37855829725716,
      "Object_Width": 84.37855829725716,
      "initial_pose": [
        824.4373753307098,
        180.63177085211046,
        0.15306402943541364
      ],
      "goal_pose": [
        807.2177455266859,
        316.6002048060207,
        0
      ]
    },
    {
      "Object_Shape": "cuboid",
      "Object_Length": 84.37855829725716,
      "Object_Width": 84.37855829725716,
      "initial_pose": [
        494.21890881766075,
        182.51324960550497,
        0.4156026727644099
      ],
      "goal_pose": [
        901.596303823943,
        316.6002048060207,
        0
      ]
    },
    {
      "Object_Shape": "cuboid",
      "Object_Length": 84.37855829725716,
      "Object_Width": 84.37855829725716,
      "initial_pose": [
        695.1377336231816,
        286.86565603944825,
        4.814881116722322
      ],
      "goal_pose": [
        52.18927914862858,
        410.9787631032779,
        0
      ]
    },
    {
      "Object_Shape": "cuboid",
      "Object_Length": 84.37855829725716,
      "Object_Width": 84.37855829725716,
      "initial_pose": [
        125.9431921462828,
        75.65266960997718,
        2.219383221919042
      ],
      "goal_pose": [
        146.56783744588574,
        410.9787631032779,
        0
      ]
    },
    {
      "Object_Shape": "cuboid",
      "Object_Length": 84.37855829725716,
      "Object_Width": 84.37855829725716,
      "initial_pose": [
        68.40329479763486,
        355.76592798085306,
        1.6362942159003628
      ],
      "goal_pose": [
        240.94639574314292,
        410.9787631032779,
        0
      ]
    },
    {
      "Object_Shape": "cuboid",
      "Object_Length": 84.37855829725716,
      "Object_Width": 84.37855829725716,
      "initial_pose": [
        655.9296812936985,
        882.3962990922236,
        0.6433989466252904
      ],
      "goal_pose": [
        335.32495404040003,
        410.9787631032779,
        0
      ]
    },
    {
      "Object_Shape": "cuboid",
      "Object_Length": 84.37855829725716,
      "Object_Width": 84.37855829725716,
      "initial_pose": [
        882.34059883162,
        931.3089517146575,
        0.1817124333614953
      ],
      "goal_pose": [
        429.7035123376572,
        410.9787631032779,
        0
      ]
    },
    {
      "Object_Shape": "cuboid",
      "Object_Length": 84.37855829725716,
      "Object_Width": 84.37855829725716,
      "initial_pose": [
        935.7321450246435,
        209.00513335469873,
        1.1999238833713626
      ],
      "goal_pose": [
        524.0820706349144,
        410.9787631032779,
        0
      ]
    },
    {
      "Object_Shape": "cuboid",
      "Object_Length": 84.37855829725716,
      "Object_Width": 84.37855829725716,
      "initial_pose": [
        940.0648396385916,
        723.0638945916289,
        1.2939559408310681
      ],
      "goal_pose": [
        618.4606289321715,
        410.9787631032779,
        0
      ]
    },
    {
      "Object_Shape": "cuboid",
      "Object_Length": 84.37855829725716,
      "Object_Width": 84.37855829725716,
      "initial_pose": [
        876.6333816103896,
        812.5248061979636,
        2.285652743516231
      ],
      "goal_pose": [
        712.8391872294287,
        410.9787631032779,
        0
      ]
    },
    {
      "Object_Shape": "cuboid",
      "Object_Length": 84.37855829725716,
      "Object_Width": 84.37855829725716,
      "initial_pose": [
        189.73785954383027,
        789.3948967867371,
        0.28075430227055637
      ],
      "goal_pose": [
        807.2177455266859,
        410.9787631032779,
        0
      ]
    },
    {
      "Object_Shape": "cuboid",
      "Object_Length": 84.37855829725716,
      "Object_Width": 84.37855829725716,
      "initial_pose": [
        368.922254130815,
        226.99811899142674,
        4.953034230194977
      ],
      "goal_pose": [
        901.596303823943,
        410.9787631032779,
        0
      ]
    },
    {
      "Object_Shape": "cuboid",
      "Object_Length": 84.37855829725716,
      "Object_Width": 84.37855829725716,
      "initial_pose": [
        555.2539617202302,
        273.20637561180547,
        3.442866864810843
      ],
      "goal_pose": [
        52.18927914862858,
        505.3573214005351,
        0
      ]
    },
    {
      "Object_Shape": "cuboid",
      "Object_Length": 84.37855829725716,
      "Object_Width": 84.37855829725716,
      "initial_pose": [
        390.354854054245,
        732.206383478447,
        4.8214016372409345
      ],
      "goal_pose": [
        146.56783744588574,
        505.3573214005351,
        0
      ]
    },
    {
      "Object_Shape": "cuboid",
      "Object_Length": 84.37855829725716,
      "Object_Width": 84.37855829725716,
      "initial_pose": [
        829.6352341076033,
        683.8223640489259,
        3.120964658965657
      ],
      "goal_pose": [
        240.94639574314292,
        505.3573214005351,
        0
      ]
    },
    {
      "Object_Shape": "cuboid",
      "Object_Length": 84.37855829725716,
      "Object_Width": 84.37855829725716,
      "initial_pose": [
        161.48301084322347,
        424.0742931428466,
        2.9817053538798923
      ],
      "goal_pose": [
        335.32495404040003,
        505.3573214005351,
        0
      ]
    },
    {
      "Object_Shape": "cuboid",
      "Object_Length": 84.37855829725716,
      "Object_Width": 84.37855829725716,
      "initial_pose": [
        567.4668727758408,
        771.0182284416575,
        5.702286938966157
      ],
      "goal_pose": [
        429.7035123376572,
        505.3573214005351,
        0
      ]
    },
    {
      "Object_Shape": "cuboid",
      "Object_Length": 84.37855829725716,
      "Object_Width": 84.37855829725716,
      "initial_pose": [
        88.45191120440987,
        509.4388555268654,
        2.63103909983765
      ],
      "goal_pose": [
        524.0820706349144,
        505.3573214005351,
        0
      ]
    },
    {
      "Object_Shape": "cuboid",
      "Object_Length": 84.37855829725716,
      "Object_Width": 84.37855829725716,
      "initial_pose": [
        76.32292980571454,
        888.5358602744489,
        3.58715269588945
      ],
      "goal_pose": [
        618.4606289321715,
        505.3573214005351,
        0
      ]
    },
    {
      "Object_Shape": "cuboid",
      "Object_Length": 84.37855829725716,
      "Object_Width": 84.37855829725716,
      "initial_pose": [
        624.5769627930509,
        527.5279185573401,
        4.427566404891516
      ],
      "goal_pose": [
        712.8391872294287,
        505.3573214005351,
        0
      ]
    }
  ]
}