{
  "Workspace_Density": 0.4,
  "Workspace_Height": 1000,
  "Workspace_Width": 1000,
  "number_of_objects": 20,
  "object_list": [
    {
      "Object_Shape": "cuboid",
      "Object_Length": 317.02131247412063,
      "Object_Width": 317.02131247412063,
      "initial_pose": [
        685.0445458001547,
        258.49217081005406,
        5.013062508589125
      ],
      "goal_pose": [
        168.51065623706032,
        168.51065623706032,
        0
      ]
    },
    {
      "Object_Shape": "cuboid",
      "Object_Length": 317.02131247412063,
      "Object_Width": 317.02131247412063,
      "initial_pose": [
        267.0882517892504,
        254.26348017898437,
        0.7049691212053675
      ],
      "goal_pose": [
        495.531968711181,
        168.51065623706032,
        0
      ]
    },
    {
      "Object_Shape": "cuboid",
      "Object_Length": 105.1440744022674,
      "Object_Width": 105.1440744022674,
      "initial_pose": [
        688.7472656355803,
        554.1691557522304,
        3.493484893305477
      ],
      "goal_pose": [
        716.6146621493749,
        62.5720372011337,
        0
      ]
    },
    {
      "Object_Shape": "cuboid",
      "Object_Length": 105.1440744022674,
      "Object_Width": 105.1440744022674,
      "initial_pose": [
        594.990991348129,
        845.9086893818718,
        3.2356285116472914
      ],
      "goal_pose": [
        831.7587365516423,
        62.5720372011337,
        0
      ]
    },
    {
      "Object_Shape": "cuboid",
      "Object_Length": 105.1440744022674,
      "Object_Width": 105.1440744022674,
      "initial_pose": [
        382.5097802119702,
        810.445618768994,
        3.9955457971129977
      ],
      "goal_pose": [
        946.9028109539097,
        62.5720372011337,
        0
      ]
    },
    {
      "Object_Shape": "cuboid",
      "Object_Length": 105.1440744022674,
      "Object_Width": 105.1440744022674,
      "initial_pose": [
        835.4414101522844,
        863.2495935109332,
        1.902401864984623
      ],
      "goal_pose": [
        716.6146621493749,
        274.44927527298694,
        0
      ]
    },
    {
      "Object_Shape": "cuboid",
      "Object_Length": 105.1440744022674,
      "Object_Width": 105.1440744022674,
      "initial_pose": [
        150.50162019604142,
        699.3479211810742,
        2.4316333751465904
      ],
      "goal_pose": [
        831.7587365516423,
        274.44927527298694,
        0
      ]
    },
    {
      "Object_Shape": "cuboid",
      "Object_Length": 105.1440744022674,
      "Object_Width": 105.1440744022674,
      "initial_pose": [
        412.34036340427895,
        604.8943547797898,
        3.9333972654689577
      ],
      "goal_pose": [
        946.9028109539097,
        274.44927527298694,
        0
      ]
    },
    {
      "Object_Shape": "cuboid",
      "Object_Length": 105.1440744022674,
      "Object_Width": 105.1440744022674,
      "initial_pose": [
        796.2832721036584,
        657.1306602956844,
        2.1534329164019237
      ],
      "goal_pose": [
        62.5720372011337,
        389.59334967525433,
        0
      ]
    },
    {
      "Object_Shape": "cuboid",
      "Object_Length": 105.1440744022674,
      "Object_Width": 105.1440744022674,
      "initial_pose": [
        455.75025994274046,
        436.369696161245,
        4.872022262622811
      ],
      "goal_pose": [
        177.71611160340112,
        389.59334967525433,
        0
      ]
    },
    {
      "Object_Shape": "cuboid",
      "Object_Length": 105.1440744022674,
      "Object_Width": 105.1440744022674,
      "initial_pose": [
        346.22021015621164,
        695.0267838554798,
        0.7699249197018541
      ],
      "goal_pose": [
        292.86018600566854,
        389.59334967525433,
        0
      ]
    },
    {
      "Object_Shape": "cuboid",
      "Object_Length": 105.1440744022674,
      "Object_Width": 105.1440744022674,
      "initial_pose": [
        634.1653412730886,
        671.120103502332,
        4.326568937227191
      ],
      "goal_pose": [
        408.00426040793593,
        389.59334967525433,
        0
      ]
    },
    {
      "Object_Shape": "cuboid",
      "Object_Length": 105.1440744022674,
      "Object_Width": 105.1440744022674,
      "initial_pose": [
        895.6726833665218,
        540.9344739682069,
        0.517798065449586
      ],
      "goal_pose": [
        523.1483348102033,
        389.59334967525433,
        0
      ]
    },
    {
      "Object_Shape": "cuboid",
      "Object_Length": 105.1440744022674,
      "Object_Width": 105.1440744022674,
      "initial_pose": [
        278.20282484002377,
        570.5831868924439,
        0.8837282086212186
      ],
      "goal_pose": [
        638.2924092124707,
        389.59334967525433,
        0
      ]
    },
    {
      "Object_Shape": "cuboid",
      "Object_Length": 105.1440744022674,
      "Object_Width": 105.1440744022674,
      "initial_pose": [
        148.32948520059452,
        870.1026828157187,
        1.0625235844535594
      ],
      "goal_pose": [
        753.4364836147381,
        389.59334967525433,
        0
      ]
    },
    {
      "Object_Shape": "cuboid",
      "Object_Length": 105.1440744022674,
      "Object_Width": 105.1440744022674,
      "initial_pose": [
        901.5595678820296,
        392.2054638665837,
        0.6311366977821097
      ],
      "goal_pose": [
        868.5805580170055,
        389.59334967525433,
        0
      ]
    },
    {
      "Object_Shape": "cuboid",
      "Object_Length": 105.1440744022674,
      "Object_Width": 105.1440744022674,
      "initial_pose": [
        912.7902484011438,
        735.2841263519146,
        0.2203660275036732
      ],
      "goal_pose": [
        62.5720372011337,
        504.7374240775218,
        0
      ]
    },
    {
      "Object_Shape": "cuboid",
      "Object_Length": 105.1440744022674,
      "Object_Width": 105.1440744022674,
      "initial_pose": [
        538.8106972917994,
        555.5694774052126,
        1.8833382356470256
      ],
      "goal_pose": [
        177.71611160340112,
        504.7374240775218,
        0
      ]
    },
    {
      "Object_Shape": "cuboid",
      "Object_Length": 105.1440744022674,
      "Object_Width": 105.1440744022674,
      "initial_pose": [
        92.23698863299067,
        103.29053585145276,
        3.562402104184616
      ],
      "goal_pose": [
        292.86018600566854,
        504.7374240775218,
        0
      ]
    },
    {
      "Object_Shape": "cuboid",
      "Object_Length": 105.1440744022674,
      "Object_Width": 105.1440744022674,
      "initial_pose": [
        853.2647934473473,
        59.293025166515356,
        6.2548975451174025
      ],
      "goal_pose": [
        408.00426040793593,
        504.7374240775218,
        0
      ]
    }
  ]
}